tradexil.py
tradexil-1.0.5.dist-info/METADATA
tradexil-1.0.5.dist-info/WHEEL
tradexil-1.0.5.dist-info/top_level.txt
tradexil-1.0.5.dist-info/RECORD
